aiagent/__init__.py
aiagent/ai_agent.py
aiagent/cli_tool.py
aiagent/dynamic_log_extractor.py
aiagent/mongodb_service.py
aiagent/setup_automated_monitoring.py
aiagent/test_cli_dashboard_integration.py
aiagent/Scripts/README_THREAT_DETECTION.md
aiagent/Scripts/__init__.py
aiagent/Scripts/accurate_test_robustness.py
aiagent/Scripts/analyze_confidence.py
aiagent/Scripts/classify_logs.py
aiagent/Scripts/confidence_classifier.py
aiagent/Scripts/cost_sensitive_evaluator.py
aiagent/Scripts/cost_sensitive_trainer.py
aiagent/Scripts/enhanced_threat_model.py
aiagent/Scripts/improved_threat_trainer.py
aiagent/Scripts/json_to_csv.py
aiagent/Scripts/prerag_classifier.py
aiagent/Scripts/pure_ml_test.py
aiagent/Scripts/quick_train.py
aiagent/Scripts/run_cost_sensitive_training.py
aiagent/Scripts/test_model_robustness.py
aiagent/Scripts/test_setup.py
aiagent/Scripts/test_trained_model.py
aiagent/Scripts/test_validation_warning.py
aiagent/Scripts/tune_threshold.py
aiagent/Scripts/verify_test_accuracy.py
aiagent/Scripts/models/improved_threat_model.joblib
aiagent/Scripts/models/quick_threat_model_20251011_185825.joblib
aiagent/Scripts/models/threat_classification_model.joblib
aiagent/Scripts/models/threat_classification_model_report.txt
logiq_cli-1.8.0.dist-info/METADATA
logiq_cli-1.8.0.dist-info/WHEEL
logiq_cli-1.8.0.dist-info/entry_points.txt
logiq_cli-1.8.0.dist-info/top_level.txt
logiq_cli-1.8.0.dist-info/RECORD
